ucc/__init__.py
ucc/_version.py
ucc/compile.py
ucc/tests/__init__.py
ucc/tests/mock_backends.py
ucc/tests/test_compile.py
ucc/transpilers/__init__.py
ucc/transpilers/ucc_bqskit.py
ucc/transpilers/ucc_defaults.py
ucc/transpilers/aqc/README.md
ucc/transpilers/aqc/__init__.py
ucc/transpilers/aqc/mps_pass.py
ucc/transpilers/aqc/mps_sequential.py
ucc/transpilers/aqc/mps_utils.py
ucc/transpilers/aqc/qmprs_compiler.py
ucc-0.4.12.dist-info/METADATA
ucc-0.4.12.dist-info/WHEEL
ucc-0.4.12.dist-info/entry_points.txt
ucc-0.4.12.dist-info/licenses/LICENSE
ucc-0.4.12.dist-info/RECORD
