Metadata-Version: 2.4
Name: ucc
Version: 0.4.12
Summary: Unitary Compiler Collection: A quantum circuit interface and compiler for multiple quantum frameworks
Author: Jordan Sullivan, Misty Wahl, Nate Stemen, Brad Chase
License-Expression: AGPL-3.0-only
License-File: LICENSE
Classifier: License :: OSI Approved :: GNU Affero General Public License v3
Requires-Python: <3.14,>=3.12
Requires-Dist: cirq-core<2.0.0,>=1.4.1
Requires-Dist: ply<4.0.0,>=3.11
Requires-Dist: pytket<3.0.0,>=1.40.0
Requires-Dist: qbraid<1.0.0,>=0.9.3
Requires-Dist: qiskit-qasm3-import<1.0.0,>=0.5.1
Requires-Dist: qiskit<3.0.0,>=1.4.2
Requires-Dist: quimb==1.11.2
